{
  "record": {
    "isbn": "9784062778299",
    "booklet": "PC脇",
    "title": "海賊とよばれた男",
    "title_source": "ndl",
    "ndc": "913.6",
    "ndc_source": "ndl",
    "ndc_version": "9",
    "ndc_version_source": "ndl",
    "author": "百田, 尚樹,百田尚樹 [著]",
    "author_source": "ndl",
    "publisher": "講談社",
    "publisher_source": "ndl",
    "pub_date": "2014",
    "pub_date_source": "ndl",
    "series": "講談社文庫 ; ひ43-7",
    "series_source": "ndl",
    "volume": "上",
    "volume_source": "ndl",
    "pages": "466",
    "pages_source": "user",
    "content": "درلمه\n序章\n第一章朱夏 昭和二十年-昭和二十二年\n一、首はならん！\n仁苦鬪\n三、ラジオ修理\nしののめただし\n四、東雲忠司\n五、GHQ\n六タンク底\n七、公職追放八，\n石統との戦い\nたけち、こうた\n九、武知甲太郎\n+”スタンバック\n干一、逆転\n9\n21\n十一、逆転\n第二章 青春 明治十八年1昭和二十年\n1\n石油との出会い\nた じゅうたろう\n11\n日田重太郎\nでつち\n三\n丁稚\n四、生家の没落\n五、士魂商才\n六、\n海賊\n七、\n满州\nスタンダードとの戦い\n九、\n危機\nせんがい\n十、仙\n十一、世界恐慌\nシヤンハイ\n十二，上海\n十三 日中戰争\n十四、石油禁輸\n十五、南方へ\n十六、敗戦\n195",
    "system_type": "notion",
    "external_book_id": "326749de-9a26-8199-bf35-ff1f014ea22c",
    "created_at": "2026-02-17 06:43:08",
    "updated_at": "2026-02-17 06:43:08",
    "cover_url": "cover/9784062778299.jpg"
  }
}