{
  "record": {
    "isbn": "9784044004347",
    "booklet": "PC脇",
    "title": "民主主義",
    "title_source": "ndl",
    "ndc": "311.7",
    "ndc_source": "ndl",
    "ndc_version": "10",
    "ndc_version_source": "ndl",
    "author": "文部省,文部省 著",
    "author_source": "ndl",
    "publisher": "KADOKAWA",
    "publisher_source": "ndl",
    "pub_date": "2018",
    "pub_date_source": "ndl",
    "series": "[角川ソフィア文庫] ; [M123-1]",
    "series_source": "ndl",
    "volume": "[M123-1]",
    "volume_source": "opendb",
    "pages": "461",
    "pages_source": "ndl",
    "content": "目次\nはしがき\n第一章民主主義の本質\n一民主主義の根本精神\n二下から上への権威\n三民主主義の国民生活\n四自由と平等\n五 民主主義の幅のひろさ\n第二章 民主主義の発達古代の民主主義\nイギリスにおける民主主義の発達\n三アメリカにおける民主主義の発達\n16\n48\n38\n37\n34\n29\n25\n21\n四 フランスにおける民主主義の発達\n第三章民主主義の諸制度\n一民主主義と反対の制度\n二民主政治の 型\n三イギリスの制度\n四アメリカの制度\n五 スイスの制度\n第四章選挙権\nー国民の代表者の選挙\n二選挙の方法\n三選挙権の拡張\n四婦人参政権\n五 選挙の権利と選挙の義務・\n103 100 95\n91\n87\n83\n77\n72\n68\n64\n57\n第力章\nT多数決\nー民主主義と多数決\n二多数決原理に対する疑問\n三民主政治の落し穴\n四多数決と言論の自由\n五多数決による政治の進歩\n第六章目ざめた有権者\n一民主主義 世論\n二宣伝とはどんなものか\n三宣伝によって国民をあざむく方法\n四宣伝機関\n五報道に対する科学的考察\n第七章政治と国民\n一人任せの政治と自分たちの政治\n148\n143 137 132\n128 125\n122 117 114 110 108\n二地方自治\n三国の政治\n四政党\n五政党政治の弊害\n第八章社会生活における民主主義\n一社会生活の民主化\n二個人の尊重\n三個人主義\n四権利と責任\n五社会道徳\n第九章経済生活における民主主義\nー自由競争の利益\n二独占の弊害\n三資本主義と社会主義\n四統制の必要とその民主化\n206 197 194 188\n183 180\n176 172 168\n162 158 155 151\n五協同組合の発達\n六消費者の保護\n第十章民主主義と労働組合\n一学働組合の目的\n二労働組合の任務\n三.產業平和の実現\n四団体交渉\n五日本の労働組合\n六労働組合の政治活動\n第十一章民主主義と独裁主義\n一民主主義の三つの側面\n二民主主義に対する非難\n三民主主義の答\n四 共産主義の立場\n五\nプロレタリアの独裁\n268\n259\n255 251 246\n241 238\n232 229\n226 222\n216 211\n六 共產主義 民主主義\n第十二章日本 民主主義の歴史\n一明治初年の自由民権運動二明治憲法の制定三明治憲法の内容\n四日本 政党政治五政党政治の末路\n第十三章新憲法 現 民主主義\n一日本国憲法の成立二国民の主権三 国会中心主義四違憲立法の審五国民の基本的権利\n324 321 315 310\n309\n302 296\n290\n288\n281\n274\n第十四章民主主義の学び方\n一民主主義を学ぶ方法\n二学校教育の刷新\n三教育の機会均等と新教育の方針\n四「民主主義の教育」の実践\n五 校友会\n六校外活動\n第十五章日本婦人の新しい権利と責任\n一婦人参政権運動\n二婦人と政治\n三これからの女子教育\n四婦人と家庭生活\n五婦人と労働\n第十六章 国際生活における民主主義\n386\n379\n375 369\n364\n359\n355\n350\n344 340\n338\n一民主主義と世界平和\n二 国際民主主義 国際連合\n三世界国家の問題\n四ユネスコ\n五日本の前途\n第十七章民主主義のもたらすもの一民主主義は何をもたらすか\n二民主主義の原動力\n三民主主義のなしうること\n四協同の力\n五討論と実行\n解説内田樹\n445\n438 431 426 420 418\n414 409 405\n397392",
    "system_type": "notion",
    "external_book_id": "330749de-9a26-8183-867c-ca81f995d148",
    "created_at": "2026-03-27 08:19:09",
    "updated_at": "2026-03-27 08:19:09",
    "cover_url": "cover/9784044004347.jpg"
  }
}