{
  "record": {
    "isbn": "9784768702956",
    "booklet": "焦茶本棚",
    "title": "初めて学ぶ統計学",
    "title_source": "ndl",
    "ndc": "417",
    "ndc_source": "ndl",
    "ndc_version": "9",
    "ndc_version_source": "ndl",
    "author": "菅, 民郎, 1943-,桧山, みぎわ, 1966-,菅民郎, 檜山みぎわ 著",
    "author_source": "ndl",
    "publisher": "現代数学社",
    "publisher_source": "ndl",
    "pub_date": "2003",
    "pub_date_source": "ndl",
    "series": "",
    "series_source": "",
    "volume": "",
    "volume_source": "",
    "pages": "242",
    "pages_source": "ndl",
    "content": "一\n統計学のスタート\n1.統計学とはなにか\n2.記述統計学と推測統計学\n記述統計学\n1.集団の特徴をとらえる～代表値でみる～\n〔解説1〕平均値\n〔解說2〕偏差平方和•\n〔解説3〕分散・標準偏差・\n〔公式）\n例題\n例題\nテスト1\n2.集団の特徴をとらえる～分布でみる～\n〔解説1〕度数分布\n〔解説2〕度数分布の平均値・標準偏差\n〔解説3〕度数分布のグラフ化\n〔公式）\n例題\nテスト\n3.個々のデータの位置を知る〔解説1〕基準値\n〔解説2〕偏差値\n〔公式）\n例題\nテスト\n1\n2\n3\n4\n3\n4.集団の特徴を分布曲線であらわす\n〔解説1〕正規分布\n〔解説2〕標準正規分布\n〔解説3〕標準正規分布表の見方\n〔公式）\n例題\n3\n7\n11\n11\n12\n14\n• 15\n16\n7\n6\n17\n18\n18\n19\n• 20\n22\n23\n25\n26\n30\n31\n32\n33\n33\n36\n37\n39\n40\n例題6\nテスト\nテスト\n4\nII 推測統計学\n1. 母集団と標本\n〔解説1〕全体と部分\n〔解説2〕ランダム抽出\n〔解説3〕統計的推定・検定\n〔解説4〕仮説的無限母集団\n2. 標本統計量の分布\n〔解説1〕標本統計量\n〔解説2〕標本平均の分布\n〔解説3〕標本分散の分布\n〔公式〕\n実験してみましょう【1】\n実験してみましょう【2】\nIV 統計的推定\n1. 統計的推定の考え方\n2.母平均の推定\n〔解説1〕Z推定\n〔解說2〕t推定\n〔解説3〕分布表の見方\n〔解説4〕有限母集団の推定\n〔公式〕\n例題\n例題\nテスト\n7\n8\n9\nテスト\n3.母比率の推定\n〔解説1〕比率\n〔解説2〕標本比率の分布\n実験してみましょう【3】・実験してみましよう【4】・\n〔解説3〕母比率のZ推定・\n〔公式）\n例題9\nテスト\n8\nV 統計的検定\n1. 統計的検定の考え方\n〔解説1〕次の例で考えてみましょう\n〔解説2〕統計的推定を用いて②を考えてみましょう\n〔解説3〕統計的推定を用いる統計的検定\n〔解説4〕1標本の検定・2標本の検定\n〔解説5〕統計的検定の公式を用いて検定を行う\n2.統計的検定のしくみ\n〔解説1〕統計的検定のしくみ\n〔解説2〕帰無仮説・対立仮説\n〔解説3〕統計量T..\n〔解説4〕有意水準と棄却域\n〔解説5〕・統計量T値を比較する\n実験してみましょう【5】\n実験してみましよう【6】\n実験してみましよう（7】\n〔解説6〕小標本の検定....\n3.1標本の 定\n〔解説1〕母平均の検定\n〔解説2〕母比率の検定\n〔公式〕\n例題\n10\n例題\ni 11\nテスト\nテスト 10\n4.2標本の検定\n79\n80\n81\n8\n∞\n87\n87\n89\n- 90\n92\n93\n• 93\n94\n96\n• 98\n• 99\n102\n• 103\n104\n• 106\n108\n108\n• 111\n-113\n115\n116\n• 117\n• 119\n120\nV\n〔解説1〕母平均の差の検定\n〔解説2〕対応のない場合の検定\n〔解説3〕対応のある場合の検定\n〔解説4〕母比率の差の検定\n〔公\n式〕\n例題\n12\n例題\n13\n例題\n14\nテスト\n11\nテスト\n12\nテスト\n13\n：\nテスト\n14\nテスト\n15\nノンパラメトリックの検定\n1.ノンパラメトリック検定とは\n2.適合度の検定\n〔解説1〕適合度の検定の考え方\n日実験してみましよう【8】\n〔解説2〕適合度の検定の手順と記述\n例題 15\nテスト16\n3.独立性の検定\n〔解説1〕独立性の検定の考え方\n例題 16\n例題 17\nテスト 17\n日 もっと理解したい方へ\n① 基本統計\n1. いろいろな代表値\n2. 偏差平方和の公式\n3.比率Pの標準偏差は何故、P（1-P）なのか\n4. 度数分布の中央値（メディアン）の求め方\n5. パーセンタイル・\n6. “ゆがみ”と”とがり”\n7. 偏差値から次のことがわかる\n8. 基準化したデータの標準偏差はなぜ1なのか\n9. 度数分布に正規分布曲線をあてはめる\n10. 理論度数をもとめる\n②母比率のF推定・F検定\n③ 母分散の推定・検定\n④ 順位データの検定①～ウィルコクソンのサインランク検定～\n⑤ 順位データの検定②～ウィルコクソンの順位和検定（U検定）～\nテストの解答\n付・分布表\n•••",
    "system_type": "notion",
    "external_book_id": "332749de-9a26-812f-94ef-df98cb1d661b",
    "created_at": "2026-03-29 23:28:31",
    "updated_at": "2026-03-29 23:28:31",
    "cover_url": "cover/9784768702956.jpg"
  }
}