{
  "page_num": 109,
  "isbns": [
    {
      "token": "子ども",
      "isbns": {
        "9784833425650": 1
      }
    },
    {
      "token": "子供たち",
      "isbns": {
        "9784047033757": 1
      }
    },
    {
      "token": "子孫",
      "isbns": {
        "9784047033757": 1,
        "9784569665511": 1
      }
    },
    {
      "token": "子育て",
      "isbns": {
        "9784166605248": 1
      }
    },
    {
      "token": "孔夫子",
      "isbns": {
        "4-8047-5021-5": 1
      }
    },
    {
      "token": "存在",
      "isbns": {
        "9784047033757": 4,
        "9784331006054": 1,
        "9784594073879": 1,
        "9784777830398": 2,
        "9784809031892": 1,
        "9784909044662": 1
      }
    },
    {
      "token": "孝俊",
      "isbns": {
        "9784047033757": 1
      }
    },
    {
      "token": "季節",
      "isbns": {
        "9784047033757": 1
      }
    },
    {
      "token": "孤独",
      "isbns": {
        "9784344032910": 7
      }
    },
    {
      "token": "孤独感",
      "isbns": {
        "9784777830398": 1
      }
    },
    {
      "token": "学ぶ",
      "isbns": {
        "4-8047-5021-5": 1,
        "9784344032910": 1,
        "9784594073879": 1,
        "9784828427669": 1,
        "9784833425650": 4
      }
    },
    {
      "token": "学べる",
      "isbns": {
        "9784569845999": 2
      }
    },
    {
      "token": "学力",
      "isbns": {
        "9784166605248": 1
      }
    },
    {
      "token": "学問",
      "isbns": {
        "4-8047-5021-5": 2,
        "9784480064707": 6
      }
    },
    {
      "token": "学校",
      "isbns": {
        "9784867931042": 1
      }
    },
    {
      "token": "学校教育",
      "isbns": {
        "9784044004347": 1
      }
    },
    {
      "token": "学芸",
      "isbns": {
        "9784047033757": 1
      }
    },
    {
      "token": "宇宙",
      "isbns": {
        "9784047033757": 7,
        "9784331006054": 21,
        "9784344032910": 1,
        "9784569665511": 3
      }
    },
    {
      "token": "宇宙論",
      "isbns": {
        "9784331006054": 1
      }
    },
    {
      "token": "宇野",
      "isbns": {
        "9784331006054": 1
      }
    }
  ]
}