{
  "page_num": 11,
  "isbns": [
    {
      "token": "天皇",
      "isbns": {
        "9784047033757": 1,
        "9784166605248": 2,
        "9784806124948": 1,
        "9784866221090": 11
      }
    },
    {
      "token": "天空",
      "isbns": {
        "9784569665511": 1
      }
    },
    {
      "token": "天道",
      "isbns": {
        "9784047033757": 1
      }
    },
    {
      "token": "太い",
      "isbns": {
        "9784806135494": 1
      }
    },
    {
      "token": "太る",
      "isbns": {
        "9784062815215": 1
      }
    },
    {
      "token": "太一",
      "isbns": {
        "9784062778305": 1
      }
    },
    {
      "token": "太子",
      "isbns": {
        "9784866221090": 2
      }
    },
    {
      "token": "太極旗",
      "isbns": {
        "9784837985815": 1
      }
    },
    {
      "token": "太良",
      "isbns": {
        "9784047033757": 5
      }
    },
    {
      "token": "太郎",
      "isbns": {
        "9784047033757": 1
      }
    },
    {
      "token": "太陽",
      "isbns": {
        "9784047033757": 8,
        "9784569665511": 5,
        "9784837985815": 1
      }
    },
    {
      "token": "太陽系",
      "isbns": {
        "9784768459416": 1
      }
    },
    {
      "token": "夫人",
      "isbns": {
        "9784309464084": 1
      }
    },
    {
      "token": "夫婦",
      "isbns": {
        "9784047033757": 1,
        "9784296109272": 1,
        "9784569645742": 1
      }
    },
    {
      "token": "夫婦関係",
      "isbns": {
        "9784569645742": 2
      }
    },
    {
      "token": "失う",
      "isbns": {
        "9784047033757": 1,
        "9784166605248": 1,
        "9784492533871": 1,
        "9784569665511": 1,
        "9784594073879": 1
      }
    },
    {
      "token": "失くす",
      "isbns": {
        "9784909044662": 1
      }
    },
    {
      "token": "失恋",
      "isbns": {
        "9784569645742": 1
      }
    },
    {
      "token": "失意",
      "isbns": {
        "4804750215": 1
      }
    },
    {
      "token": "失敗",
      "isbns": {
        "4804750215": 2,
        "9784296109272": 1,
        "9784339023992": 1,
        "9784569665511": 1,
        "9784569764085": 4,
        "9784798100234": 8,
        "9784828427669": 3,
        "9784833425650": 1,
        "9784894518049": 7
      }
    },
    {
      "token": "奇妙",
      "isbns": {
        "9784120043079": 1
      }
    },
    {
      "token": "奇跡",
      "isbns": {
        "9784062778305": 1,
        "9784562032495": 1,
        "9784569648866": 5,
        "9784866802565": 3,
        "9784894518049": 2,
        "9784909044662": 2
      }
    },
    {
      "token": "奈良",
      "isbns": {
        "9784816354090": 1,
        "9784866221090": 1
      }
    },
    {
      "token": "契約",
      "isbns": {
        "9784322130560": 5,
        "9784569764085": 3
      }
    },
    {
      "token": "女子",
      "isbns": {
        "9784044004347": 1,
        "9784489020001": 1
      }
    },
    {
      "token": "女帝",
      "isbns": {
        "9784569665511": 1
      }
    },
    {
      "token": "女性",
      "isbns": {
        "9784047033757": 1,
        "9784120043079": 1,
        "9784296109272": 3
      }
    },
    {
      "token": "女性器",
      "isbns": {
        "9784047033757": 1
      }
    },
    {
      "token": "女房",
      "isbns": {
        "9784047033757": 1
      }
    },
    {
      "token": "女神",
      "isbns": {
        "9784047033757": 7,
        "9784569665511": 5
      }
    },
    {
      "token": "奴隷制",
      "isbns": {
        "9784120043079": 1
      }
    },
    {
      "token": "好き",
      "isbns": {
        "9784041041413": 1
      }
    },
    {
      "token": "好き嫌い",
      "isbns": {
        "9784046014382": 1
      }
    },
    {
      "token": "好み",
      "isbns": {
        "9784489020001": 1
      }
    },
    {
      "token": "好む",
      "isbns": {
        "9784569764085": 1
      }
    },
    {
      "token": "好奇心",
      "isbns": {
        "9784777830398": 1
      }
    },
    {
      "token": "如し",
      "isbns": {
        "4804750215": 2
      }
    },
    {
      "token": "始まり",
      "isbns": {
        "9784062815215": 1,
        "9784140812723": 1,
        "9784866802565": 1
      }
    },
    {
      "token": "始まる",
      "isbns": {
        "9784569665511": 1,
        "9784768459416": 3,
        "9784777830398": 1
      }
    },
    {
      "token": "始める",
      "isbns": {
        "9784569764085": 3,
        "9784809031892": 2,
        "9784873118338": 4
      }
    },
    {
      "token": "始新世",
      "isbns": {
        "9784309254548": 1
      }
    },
    {
      "token": "始祖",
      "isbns": {
        "9784047033757": 4
      }
    },
    {
      "token": "委任",
      "isbns": {
        "9784322130560": 1,
        "9784569764085": 1
      }
    },
    {
      "token": "委員会",
      "isbns": {
        "9784799111406": 2
      }
    },
    {
      "token": "姿勢",
      "isbns": {
        "9784492533871": 1
      }
    },
    {
      "token": "婚姻",
      "isbns": {
        "9784047033757": 1
      }
    },
    {
      "token": "婦人",
      "isbns": {
        "9784044004347": 5
      }
    },
    {
      "token": "媒介",
      "isbns": {
        "9784322130560": 2
      }
    },
    {
      "token": "嫌い",
      "isbns": {
        "9784594073879": 2
      }
    },
    {
      "token": "嫌う",
      "isbns": {
        "9784309254548": 1
      }
    },
    {
      "token": "嫌悪",
      "isbns": {
        "9784062815215": 1
      }
    },
    {
      "token": "子ども",
      "isbns": {
        "9784569645742": 2,
        "9784833425650": 1
      }
    },
    {
      "token": "子孫",
      "isbns": {
        "9784047033757": 1,
        "9784569665511": 1
      }
    },
    {
      "token": "子宮",
      "isbns": {
        "9784816354090": 1
      }
    },
    {
      "token": "子育て",
      "isbns": {
        "9784166605248": 1
      }
    },
    {
      "token": "孔夫子",
      "isbns": {
        "4804750215": 1
      }
    },
    {
      "token": "字面",
      "isbns": {
        "9784883927616": 1
      }
    },
    {
      "token": "存在",
      "isbns": {
        "9784047033757": 4,
        "9784309254548": 1,
        "9784331006054": 1,
        "9784569645742": 1,
        "9784569648866": 2,
        "9784594073879": 1,
        "9784768459416": 4,
        "9784777830398": 2,
        "9784809031892": 1,
        "9784837985815": 1,
        "9784909044662": 1
      }
    },
    {
      "token": "存在感",
      "isbns": {
        "456003334": 1
      }
    },
    {
      "token": "孝俊",
      "isbns": {
        "9784047033757": 1
      }
    },
    {
      "token": "季節風",
      "isbns": {
        "9784062923910": 1
      }
    },
    {
      "token": "季語",
      "isbns": {
        "9784062923910": 1
      }
    },
    {
      "token": "孤独",
      "isbns": {
        "9784344032910": 7
      }
    },
    {
      "token": "孤独感",
      "isbns": {
        "9784569645742": 1,
        "9784777830398": 1
      }
    },
    {
      "token": "孤立",
      "isbns": {
        "9784166605248": 1
      }
    },
    {
      "token": "学び",
      "isbns": {
        "9784569645742": 2,
        "9784569648866": 1,
        "9784799111406": 1
      }
    },
    {
      "token": "学ぶ",
      "isbns": {
        "4804750215": 1,
        "9784041041413": 2,
        "9784044004347": 2,
        "9784296109272": 1,
        "9784344032910": 1,
        "9784569645742": 3,
        "9784594073879": 1,
        "9784768702956": 5,
        "9784799111406": 10,
        "9784828427669": 1,
        "9784833425650": 4
      }
    },
    {
      "token": "学べる",
      "isbns": {
        "9784569845999": 2
      }
    },
    {
      "token": "学力",
      "isbns": {
        "9784166605248": 1
      }
    },
    {
      "token": "学問",
      "isbns": {
        "4804750215": 1,
        "9784041041413": 1,
        "9784480064707": 7,
        "9784799111406": 9
      }
    },
    {
      "token": "学校",
      "isbns": {
        "9784799111406": 1,
        "9784867931042": 1
      }
    },
    {
      "token": "学校教育",
      "isbns": {
        "9784044004347": 1
      }
    },
    {
      "token": "学派",
      "isbns": {
        "9784768459416": 3
      }
    },
    {
      "token": "学生",
      "isbns": {
        "9784489020001": 1
      }
    },
    {
      "token": "学習",
      "isbns": {
        "9784254102772": 2,
        "9784274131493": 22,
        "9784297117160": 16,
        "9784627847125": 15
      }
    },
    {
      "token": "学術",
      "isbns": {
        "9784768459416": 1
      }
    },
    {
      "token": "学識",
      "isbns": {
        "9784309464084": 1
      }
    },
    {
      "token": "宅地",
      "isbns": {
        "9784322130560": 1
      }
    },
    {
      "token": "宅地建物取引士",
      "isbns": {
        "9784322130560": 2
      }
    },
    {
      "token": "宅地建物取引業",
      "isbns": {
        "9784322130560": 2
      }
    },
    {
      "token": "宅建",
      "isbns": {
        "9784322130560": 7
      }
    },
    {
      "token": "宅建業",
      "isbns": {
        "9784322130560": 2
      }
    },
    {
      "token": "宅建業法",
      "isbns": {
        "9784322130560": 1
      }
    },
    {
      "token": "宅急便",
      "isbns": {
        "9784569764085": 1
      }
    },
    {
      "token": "宇宙",
      "isbns": {
        "9784047033757": 4,
        "9784331006054": 21,
        "9784344032910": 1,
        "9784569648866": 1,
        "9784569665511": 3,
        "9784768459416": 2
      }
    },
    {
      "token": "宇宙論",
      "isbns": {
        "9784331006054": 1,
        "9784768459416": 1
      }
    },
    {
      "token": "宇野",
      "isbns": {
        "9784331006054": 1
      }
    },
    {
      "token": "守る",
      "isbns": {
        "9784405105201": 1,
        "9784405108059": 1,
        "9784594073879": 2,
        "9784777830398": 1,
        "9784806124948": 1
      }
    },
    {
      "token": "守れる",
      "isbns": {
        "9784166605248": 1
      }
    },
    {
      "token": "守護",
      "isbns": {
        "9784569665511": 1
      }
    },
    {
      "token": "守護神",
      "isbns": {
        "9784569665511": 1
      }
    },
    {
      "token": "守護者",
      "isbns": {
        "9784569665511": 1
      }
    },
    {
      "token": "安い",
      "isbns": {
        "9784833425650": 1,
        "9784894518049": 1
      }
    },
    {
      "token": "安保",
      "isbns": {
        "9784166605248": 1
      }
    },
    {
      "token": "安全",
      "isbns": {
        "9784344032910": 4,
        "9784405108059": 1,
        "9784809031892": 3
      }
    },
    {
      "token": "安全弁",
      "isbns": {
        "9784296109272": 1
      }
    },
    {
      "token": "安全性",
      "isbns": {
        "9784873118338": 1
      }
    },
    {
      "token": "安南",
      "isbns": {
        "9784309464084": 1
      }
    },
    {
      "token": "安売り",
      "isbns": {
        "9784894518049": 1
      }
    },
    {
      "token": "安定",
      "isbns": {
        "9784768459416": 1,
        "9784828427669": 1
      }
    },
    {
      "token": "安定期",
      "isbns": {
        "9784569845999": 1
      }
    },
    {
      "token": "安心",
      "isbns": {
        "9784344032910": 6
      }
    },
    {
      "token": "安心感",
      "isbns": {
        "9784866802565": 1
      }
    },
    {
      "token": "安易",
      "isbns": {
        "9784833425650": 1
      }
    },
    {
      "token": "安泰",
      "isbns": {
        "9784828427669": 1
      }
    },
    {
      "token": "安藤",
      "isbns": {
        "9784254102772": 1
      }
    },
    {
      "token": "完全",
      "isbns": {
        "9784062778305": 1,
        "9784569645742": 1
      }
    },
    {
      "token": "完成",
      "isbns": {
        "9784768459416": 1
      }
    },
    {
      "token": "宗教",
      "isbns": {
        "9784569648866": 2,
        "9784806124948": 1,
        "9784816354090": 1
      }
    },
    {
      "token": "宗教的",
      "isbns": {
        "9784569648866": 1,
        "9784806124948": 1
      }
    },
    {
      "token": "官僚",
      "isbns": {
        "9784862760401": 1
      }
    },
    {
      "token": "官民",
      "isbns": {
        "9784166605248": 1
      }
    },
    {
      "token": "官能",
      "isbns": {
        "9784534047816": 1
      }
    },
    {
      "token": "定型",
      "isbns": {
        "9784254102772": 1
      }
    },
    {
      "token": "定式化",
      "isbns": {
        "9784627847125": 1
      }
    },
    {
      "token": "定期",
      "isbns": {
        "9784322130560": 2
      }
    },
    {
      "token": "定期的",
      "isbns": {
        "9784873118338": 1
      }
    },
    {
      "token": "定理",
      "isbns": {
        "9784130420655": 6,
        "9784274131493": 2
      }
    },
    {
      "token": "定着",
      "isbns": {
        "9784806135494": 1,
        "9784894512443": 1
      }
    },
    {
      "token": "定義",
      "isbns": {
        "9784047033757": 3,
        "9784130420655": 1,
        "9784296109272": 1,
        "9784339023992": 1,
        "9784489020001": 1,
        "9784534047816": 2,
        "9784569645742": 1,
        "9784569845999": 2,
        "9784627847125": 3,
        "9784785310936": 1,
        "9784867931042": 1
      }
    },
    {
      "token": "定評",
      "isbns": {
        "9784883927616": 1
      }
    },
    {
      "token": "定説",
      "isbns": {
        "9784331006054": 1
      }
    },
    {
      "token": "宛先",
      "isbns": {
        "9784867931042": 1
      }
    },
    {
      "token": "宝くじ",
      "isbns": {
        "9784894512443": 1
      }
    },
    {
      "token": "宝来",
      "isbns": {
        "9784799111406": 1
      }
    },
    {
      "token": "宝物",
      "isbns": {
        "9784562032495": 1
      }
    },
    {
      "token": "実体",
      "isbns": {
        "9784569845999": 1
      }
    },
    {
      "token": "実例",
      "isbns": {
        "4804750215": 1,
        "9784331006054": 1
      }
    },
    {
      "token": "実像",
      "isbns": {
        "9784569648866": 1
      }
    },
    {
      "token": "実力",
      "isbns": {
        "9784046014382": 1,
        "9784806140078": 1,
        "9784894518049": 1
      }
    },
    {
      "token": "実在",
      "isbns": {
        "9784534047816": 1,
        "9784569665511": 1,
        "9784594073879": 1,
        "9784768459416": 1
      }
    },
    {
      "token": "実在性",
      "isbns": {
        "9784569648866": 1
      }
    },
    {
      "token": "実存",
      "isbns": {
        "9784768459416": 3
      }
    },
    {
      "token": "実学",
      "isbns": {
        "9784799111406": 1
      }
    },
    {
      "token": "実弟",
      "isbns": {
        "9784569665511": 1
      }
    },
    {
      "token": "実感",
      "isbns": {
        "9784489020001": 1
      }
    },
    {
      "token": "実戦",
      "isbns": {
        "9784041041413": 1,
        "9784806135494": 1
      }
    },
    {
      "token": "実施",
      "isbns": {
        "9784806140078": 1
      }
    },
    {
      "token": "実業",
      "isbns": {
        "4804750215": 2
      }
    },
    {
      "token": "実現",
      "isbns": {
        "9784044004347": 1,
        "9784339023992": 1,
        "9784627847125": 1,
        "9784809031892": 1,
        "9784894512443": 1
      }
    },
    {
      "token": "実用",
      "isbns": {
        "9784534047816": 1
      }
    },
    {
      "token": "実用性",
      "isbns": {
        "9784873118338": 1
      }
    },
    {
      "token": "実用的",
      "isbns": {
        "4804750215": 1
      }
    },
    {
      "token": "実績",
      "isbns": {
        "9784798100234": 2,
        "9784894512443": 2
      }
    },
    {
      "token": "実行",
      "isbns": {
        "9784044004347": 1,
        "9784339023992": 1,
        "9784806124948": 1,
        "9784894518049": 1
      }
    },
    {
      "token": "実行力",
      "isbns": {
        "9784480064707": 1
      }
    },
    {
      "token": "実装",
      "isbns": {
        "9784627847125": 1,
        "9784873118338": 1
      }
    },
    {
      "token": "実践",
      "isbns": {
        "9784044004347": 1,
        "9784627847125": 1,
        "9784806135494": 3,
        "9784833425650": 1,
        "9784873118338": 1
      }
    },
    {
      "token": "実践的",
      "isbns": {
        "9784627847125": 1
      }
    },
    {
      "token": "実際",
      "isbns": {
        "4804750215": 1,
        "9784254102772": 1,
        "9784339023992": 2,
        "9784489020001": 1,
        "9784627847125": 1,
        "9784816354090": 1
      }
    },
    {
      "token": "実験",
      "isbns": {
        "9784331006054": 1,
        "9784627847125": 1,
        "9784768702956": 8,
        "9784777830398": 1,
        "9784816354090": 1,
        "9784873118338": 20
      }
    },
    {
      "token": "実験室",
      "isbns": {
        "9784534047816": 3
      }
    },
    {
      "token": "実験的",
      "isbns": {
        "9784309464084": 1
      }
    },
    {
      "token": "宣伝",
      "isbns": {
        "9784044004347": 3,
        "9784894518049": 1
      }
    },
    {
      "token": "宣告",
      "isbns": {
        "9784768459416": 1
      }
    },
    {
      "token": "室町時代",
      "isbns": {
        "9784866221090": 1
      }
    },
    {
      "token": "宮古島",
      "isbns": {
        "9784047033757": 1
      }
    },
    {
      "token": "宮本",
      "isbns": {
        "9784254102772": 3
      }
    },
    {
      "token": "宮本武蔵",
      "isbns": {
        "9784806124948": 1
      }
    },
    {
      "token": "害悪",
      "isbns": {
        "9784480064707": 1
      }
    },
    {
      "token": "家庭",
      "isbns": {
        "9784044004347": 1,
        "9784492533871": 2,
        "9784777830398": 1
      }
    },
    {
      "token": "家族",
      "isbns": {
        "9784166605248": 3,
        "9784569645742": 3,
        "9784777830398": 6
      }
    },
    {
      "token": "家来",
      "isbns": {
        "9784909044662": 1
      }
    },
    {
      "token": "家系",
      "isbns": {
        "9784806124948": 2
      }
    },
    {
      "token": "宸筆",
      "isbns": {
        "9784866221090": 1
      }
    },
    {
      "token": "宸翰",
      "isbns": {
        "9784866221090": 2
      }
    },
    {
      "token": "宸記",
      "isbns": {
        "9784866221090": 4
      }
    },
    {
      "token": "容積率",
      "isbns": {
        "9784322130560": 1
      }
    },
    {
      "token": "寄り添う",
      "isbns": {
        "9784777830398": 1
      }
    },
    {
      "token": "寄与",
      "isbns": {
        "9784489020001": 2
      }
    },
    {
      "token": "密度",
      "isbns": {
        "9784627847125": 1
      }
    },
    {
      "token": "富む",
      "isbns": {
        "9784492533871": 1,
        "9784806124948": 1
      }
    },
    {
      "token": "富豪",
      "isbns": {
        "4804750215": 1
      }
    },
    {
      "token": "富貴",
      "isbns": {
        "4804750215": 2
      }
    },
    {
      "token": "寝息",
      "isbns": {
        "9784408421049": 1
      }
    },
    {
      "token": "寬平",
      "isbns": {
        "9784866221090": 1
      }
    },
    {
      "token": "対する",
      "isbns": {
        "9784044004347": 3,
        "9784130420655": 1,
        "9784274131493": 3,
        "9784339023992": 2,
        "9784492533871": 1,
        "9784569764085": 1,
        "9784627847125": 1,
        "9784798100234": 1,
        "9784806124948": 1,
        "9784816354090": 1,
        "9784828427669": 1,
        "9784873118338": 1
      }
    },
    {
      "token": "対世",
      "isbns": {
        "9784569764085": 2
      }
    },
    {
      "token": "対峙",
      "isbns": {
        "9784806135494": 1
      }
    },
    {
      "token": "対応",
      "isbns": {
        "9784062923910": 2,
        "9784768702956": 2,
        "9784798100234": 3,
        "9784806124948": 1,
        "9784806140078": 1,
        "9784809031892": 1
      }
    },
    {
      "token": "対数",
      "isbns": {
        "9784130420655": 1
      }
    },
    {
      "token": "対称",
      "isbns": {
        "9784785310936": 1
      }
    },
    {
      "token": "対称性",
      "isbns": {
        "9784331006054": 1
      }
    },
    {
      "token": "対立",
      "isbns": {
        "9784768702956": 1,
        "9784806135494": 1
      }
    },
    {
      "token": "対等",
      "isbns": {
        "9784166605248": 1
      }
    },
    {
      "token": "対策",
      "isbns": {
        "9784322130560": 1,
        "9784569645742": 1
      }
    },
    {
      "token": "対角化",
      "isbns": {
        "9784785310936": 3
      }
    },
    {
      "token": "対話",
      "isbns": {
        "9784569648866": 1,
        "9784627847125": 10,
        "9784894518049": 1
      }
    },
    {
      "token": "対談",
      "isbns": {
        "9784594073879": 1
      }
    },
    {
      "token": "対象",
      "isbns": {
        "9784331006054": 1
      }
    },
    {
      "token": "対面",
      "isbns": {
        "9784062815215": 1
      }
    },
    {
      "token": "寿司",
      "isbns": {
        "9784828427669": 1
      }
    },
    {
      "token": "寿命",
      "isbns": {
        "9784166605248": 2,
        "9784492533871": 1
      }
    },
    {
      "token": "封印",
      "isbns": {
        "9784331006054": 1,
        "9784569645742": 1,
        "9784569665511": 1
      }
    },
    {
      "token": "専門家",
      "isbns": {
        "9784046014382": 1,
        "9784166605248": 1,
        "9784569845999": 1,
        "9784777830398": 1
      }
    },
    {
      "token": "射る",
      "isbns": {
        "9784798100234": 1
      }
    },
    {
      "token": "射程",
      "isbns": {
        "9784806140078": 1
      }
    },
    {
      "token": "尊徳",
      "isbns": {
        "4804750215": 1
      }
    },
    {
      "token": "尊敬",
      "isbns": {
        "9784569665511": 1
      }
    },
    {
      "token": "尊重",
      "isbns": {
        "9784044004347": 1
      }
    },
    {
      "token": "導く",
      "isbns": {
        "9784627847125": 1,
        "9784777830398": 1,
        "9784894518049": 1
      }
    },
    {
      "token": "導入",
      "isbns": {
        "9784339023992": 1,
        "9784806140078": 1,
        "9784837985815": 1
      }
    },
    {
      "token": "小さい",
      "isbns": {
        "9784627847125": 1
      }
    },
    {
      "token": "小さな",
      "isbns": {
        "9784062815215": 1,
        "9784166605248": 1,
        "9784480427274": 5,
        "9784798100234": 1,
        "9784883927616": 1
      }
    },
    {
      "token": "小円",
      "isbns": {
        "9784331006054": 1
      }
    },
    {
      "token": "小刻み",
      "isbns": {
        "9784569764085": 1
      }
    },
    {
      "token": "小学校",
      "isbns": {
        "9784866802565": 1
      }
    },
    {
      "token": "小数点",
      "isbns": {
        "9784297117160": 2
      }
    },
    {
      "token": "小林",
      "isbns": {
        "9784331006054": 1
      }
    },
    {
      "token": "小熊座",
      "isbns": {
        "9784047033757": 1
      }
    },
    {
      "token": "小石川",
      "isbns": {
        "9784816354090": 1
      }
    },
    {
      "token": "小規模",
      "isbns": {
        "9784798100234": 1
      }
    },
    {
      "token": "少し",
      "isbns": {
        "9784777830398": 1,
        "9784806135494": 1
      }
    },
    {
      "token": "少ない",
      "isbns": {
        "9784274131493": 1,
        "9784806124948": 1
      }
    },
    {
      "token": "少子",
      "isbns": {
        "9784166605248": 1
      }
    },
    {
      "token": "少数",
      "isbns": {
        "9784047033757": 1
      }
    },
    {
      "token": "尖麻",
      "isbns": {
        "9784405108059": 1
      }
    },
    {
      "token": "尚紀",
      "isbns": {
        "9784309464084": 1
      }
    },
    {
      "token": "尤も",
      "isbns": {
        "9784274131493": 1
      }
    },
    {
      "token": "尤度",
      "isbns": {
        "9784489020001": 2
      }
    },
    {
      "token": "就いて",
      "isbns": {
        "9784866221090": 1
      }
    },
    {
      "token": "就活",
      "isbns": {
        "9784828427669": 1
      }
    },
    {
      "token": "尺度",
      "isbns": {
        "9784130420655": 1
      }
    },
    {
      "token": "尻尾",
      "isbns": {
        "9784833425650": 1
      }
    },
    {
      "token": "尽きる",
      "isbns": {
        "9784837985815": 1
      }
    },
    {
      "token": "尽く",
      "isbns": {
        "9784768459416": 1
      }
    },
    {
      "token": "尽くす",
      "isbns": {
        "9784569845999": 1
      }
    },
    {
      "token": "尽す",
      "isbns": {
        "4804750215": 1
      }
    },
    {
      "token": "局面",
      "isbns": {
        "9784569764085": 2
      }
    },
    {
      "token": "屁理屈",
      "isbns": {
        "9784408421049": 1
      }
    },
    {
      "token": "居留地",
      "isbns": {
        "9784480427274": 1
      }
    },
    {
      "token": "居酒屋",
      "isbns": {
        "9784799111406": 1,
        "9784866802565": 1
      }
    },
    {
      "token": "届く",
      "isbns": {
        "9784777830398": 1,
        "9784837985815": 1
      }
    },
    {
      "token": "届出制",
      "isbns": {
        "9784322130560": 2
      }
    },
    {
      "token": "屋根",
      "isbns": {
        "9784062923910": 1
      }
    },
    {
      "token": "展望",
      "isbns": {
        "9784768459416": 1
      }
    },
    {
      "token": "展開",
      "isbns": {
        "9784047033757": 1,
        "9784274131493": 5,
        "9784768459416": 1,
        "9784785310936": 1,
        "9784806135494": 2
      }
    },
    {
      "token": "展開図",
      "isbns": {
        "9784416808313": 1
      }
    },
    {
      "token": "属性",
      "isbns": {
        "9784297117160": 1,
        "9784339023992": 3,
        "9784862555267": 7
      }
    },
    {
      "token": "履行",
      "isbns": {
        "9784322130560": 1
      }
    },
    {
      "token": "山の神",
      "isbns": {
        "9784047033757": 1
      }
    },
    {
      "token": "山中",
      "isbns": {
        "9784331006054": 1
      }
    },
    {
      "token": "山姥",
      "isbns": {
        "9784047033757": 1
      }
    },
    {
      "token": "山本",
      "isbns": {
        "9784047033757": 1
      }
    },
    {
      "token": "山火事",
      "isbns": {
        "9784309254548": 5,
        "9784883927616": 1
      }
    },
    {
      "token": "山田",
      "isbns": {
        "9784867931042": 1
      }
    },
    {
      "token": "山神",
      "isbns": {
        "9784047033757": 2
      }
    },
    {
      "token": "岡田",
      "isbns": {
        "9784062923910": 1,
        "9784594073879": 1
      }
    },
    {
      "token": "岩月",
      "isbns": {
        "9784254102772": 2
      }
    },
    {
      "token": "岩石学",
      "isbns": {
        "9784309254548": 1
      }
    },
    {
      "token": "岸辺",
      "isbns": {
        "9784883927616": 1
      }
    },
    {
      "token": "崇拝",
      "isbns": {
        "9784047033757": 1
      }
    },
    {
      "token": "崇祖",
      "isbns": {
        "9784806124948": 1
      }
    },
    {
      "token": "崩壊",
      "isbns": {
        "9784492533871": 1
      }
    },
    {
      "token": "川上",
      "isbns": {
        "9784569845999": 6,
        "9784594073879": 1
      }
    },
    {
      "token": "川下",
      "isbns": {
        "9784569845999": 6
      }
    },
    {
      "token": "工事",
      "isbns": {
        "9784816354090": 1
      }
    },
    {
      "token": "工作",
      "isbns": {
        "9784416808313": 4
      }
    },
    {
      "token": "工場見学",
      "isbns": {
        "9784806135494": 1
      }
    },
    {
      "token": "工夫",
      "isbns": {
        "9784569764085": 1,
        "9784627847125": 1,
        "9784833425650": 1
      }
    },
    {
      "token": "工学",
      "isbns": {
        "9784873118338": 6
      }
    },
    {
      "token": "工業",
      "isbns": {
        "9784120043079": 1
      }
    },
    {
      "token": "左右",
      "isbns": {
        "9784166605248": 1,
        "9784569764085": 1,
        "9784777830398": 1
      }
    },
    {
      "token": "巧み",
      "isbns": {
        "9784569764085": 1
      }
    },
    {
      "token": "巨人",
      "isbns": {
        "9784047033757": 1,
        "9784562032495": 1,
        "9784569665511": 1,
        "9784806124948": 1,
        "9784883927616": 1
      }
    },
    {
      "token": "巨大",
      "isbns": {
        "9784569665511": 1,
        "9784798100234": 5,
        "9784837985815": 1
      }
    },
    {
      "token": "巨神",
      "isbns": {
        "9784569665511": 1
      }
    },
    {
      "token": "差別化",
      "isbns": {
        "9784806140078": 1
      }
    },
    {
      "token": "差異",
      "isbns": {
        "9784867931042": 1
      }
    },
    {
      "token": "巻きつける",
      "isbns": {
        "9784309464084": 1
      }
    },
    {
      "token": "巻末",
      "isbns": {
        "9784344032910": 1,
        "9784534047816": 1
      }
    },
    {
      "token": "巾着",
      "isbns": {
        "9784883927616": 1
      }
    },
    {
      "token": "市場",
      "isbns": {
        "9784798100234": 13,
        "9784806135494": 1,
        "9784806140078": 8
      }
    },
    {
      "token": "市場シェア",
      "isbns": {
        "9784806140078": 4
      }
    },
    {
      "token": "市民",
      "isbns": {
        "9784140812723": 1,
        "9784166605248": 1
      }
    },
    {
      "token": "市況",
      "isbns": {
        "9784798100234": 1
      }
    },
    {
      "token": "希典",
      "isbns": {
        "9784594073879": 1
      }
    },
    {
      "token": "希望",
      "isbns": {
        "4804750215": 1
      }
    },
    {
      "token": "带限",
      "isbns": {
        "9784806135494": 1
      }
    },
    {
      "token": "席々",
      "isbns": {
        "9784806135494": 1
      }
    },
    {
      "token": "帰る",
      "isbns": {
        "9784594073879": 1
      }
    },
    {
      "token": "帰宅",
      "isbns": {
        "9784296109272": 1
      }
    },
    {
      "token": "帰属",
      "isbns": {
        "9784166605248": 1
      }
    },
    {
      "token": "帰無",
      "isbns": {
        "9784768702956": 1
      }
    },
    {
      "token": "帳簿",
      "isbns": {
        "9784322130560": 1
      }
    },
    {
      "token": "常世の国",
      "isbns": {
        "9784047033757": 1
      }
    },
    {
      "token": "常若",
      "isbns": {
        "9784047033757": 1
      }
    },
    {
      "token": "常識",
      "isbns": {
        "4804750215": 2,
        "9784569764085": 1,
        "9784799111406": 1
      }
    },
    {
      "token": "幕末",
      "isbns": {
        "9784166605248": 1
      }
    },
    {
      "token": "平和",
      "isbns": {
        "9784044004347": 2,
        "9784809031892": 1
      }
    },
    {
      "token": "平均",
      "isbns": {
        "9784130420655": 2,
        "9784166605248": 1,
        "9784274131493": 2,
        "9784492533871": 1,
        "9784768702956": 4
      }
    },
    {
      "token": "平均値",
      "isbns": {
        "9784768702956": 2,
        "9784909044662": 1
      }
    },
    {
      "token": "平安",
      "isbns": {
        "9784569665511": 1,
        "9784866221090": 1
      }
    },
    {
      "token": "平方和",
      "isbns": {
        "9784768702956": 2
      }
    },
    {
      "token": "平生",
      "isbns": {
        "4804750215": 1
      }
    },
    {
      "token": "平等",
      "isbns": {
        "4804750215": 1,
        "9784044004347": 1,
        "9784569645742": 1,
        "9784799111406": 2,
        "9784837985815": 1
      }
    },
    {
      "token": "平行",
      "isbns": {
        "9784416808313": 1
      }
    },
    {
      "token": "平衡",
      "isbns": {
        "9784534047816": 9
      }
    },
    {
      "token": "平面",
      "isbns": {
        "9784130420655": 1,
        "9784274131493": 1,
        "9784627847125": 1,
        "9784785310936": 1
      }
    },
    {
      "token": "年代記",
      "isbns": {
        "9784569665511": 1
      }
    },
    {
      "token": "年収",
      "isbns": {
        "9784041041413": 1
      }
    },
    {
      "token": "年版",
      "isbns": {
        "9784309464084": 2
      }
    },
    {
      "token": "年金",
      "isbns": {
        "9784166605248": 3
      }
    },
    {
      "token": "年金一元化",
      "isbns": {
        "9784166605248": 1
      }
    },
    {
      "token": "年間",
      "isbns": {
        "9784296109272": 2,
        "9784569645742": 1,
        "9784837985815": 1,
        "9784909044662": 1
      }
    },
    {
      "token": "年齢",
      "isbns": {
        "9784046014382": 1
      }
    },
    {
      "token": "幸せ",
      "isbns": {
        "9784140812723": 1,
        "9784777830398": 11,
        "9784833425650": 1,
        "9784866802565": 1
      }
    },
    {
      "token": "幸福",
      "isbns": {
        "9784777830398": 2
      }
    },
    {
      "token": "幻想",
      "isbns": {
        "9784120043079": 1,
        "9784833425650": 1,
        "9784862555267": 6
      }
    },
    {
      "token": "幻想的",
      "isbns": {
        "9784562032495": 1
      }
    },
    {
      "token": "幻獣",
      "isbns": {
        "9784309464084": 5
      }
    },
    {
      "token": "幻覚剤",
      "isbns": {
        "9784816354090": 2
      }
    },
    {
      "token": "幼少期",
      "isbns": {
        "9784777830398": 1
      }
    },
    {
      "token": "幼時",
      "isbns": {
        "4804750215": 1
      }
    },
    {
      "token": "幼虫",
      "isbns": {
        "9784405105201": 1
      }
    },
    {
      "token": "幽霊",
      "isbns": {
        "9784569648866": 2,
        "9784799111406": 1
      }
    },
    {
      "token": "幾何",
      "isbns": {
        "9784130420655": 2,
        "9784339023992": 3
      }
    },
    {
      "token": "広い",
      "isbns": {
        "9784894512443": 1
      }
    },
    {
      "token": "広がり",
      "isbns": {
        "9784047033757": 1,
        "9784627847125": 1
      }
    },
    {
      "token": "広がる",
      "isbns": {
        "9784140812723": 1,
        "9784331006054": 1,
        "9784569665511": 1,
        "9784768459416": 1,
        "9784833425650": 2
      }
    },
    {
      "token": "広げる",
      "isbns": {
        "9784492533871": 1,
        "9784833425650": 1
      }
    },
    {
      "token": "広める",
      "isbns": {
        "9784254102772": 1
      }
    },
    {
      "token": "広告",
      "isbns": {
        "9784140812723": 1,
        "9784322130560": 1,
        "9784894518049": 3,
        "9784909044662": 1
      }
    },
    {
      "token": "広告代理店",
      "isbns": {
        "9784894518049": 1
      }
    },
    {
      "token": "広大",
      "isbns": {
        "9784768459416": 1
      }
    },
    {
      "token": "広島大学",
      "isbns": {
        "9784837985815": 1
      }
    },
    {
      "token": "序文",
      "isbns": {
        "9784130420655": 1,
        "9784309254548": 1,
        "9784492533871": 1,
        "9784562032495": 1,
        "9784862760401": 1
      }
    },
    {
      "token": "序章",
      "isbns": {
        "9784062778299": 1,
        "9784120043079": 1,
        "9784480427274": 1,
        "9784492533871": 1,
        "9784798100234": 1,
        "9784809031892": 1,
        "9784862555267": 1
      }
    },
    {
      "token": "序言",
      "isbns": {
        "9784062923910": 1
      }
    },
    {
      "token": "序論",
      "isbns": {
        "9784047033757": 1
      }
    },
    {
      "token": "店主",
      "isbns": {
        "9784594073879": 1
      }
    },
    {
      "token": "店員",
      "isbns": {
        "9784833425650": 1
      }
    },
    {
      "token": "度数",
      "isbns": {
        "9784130420655": 1,
        "9784768702956": 6
      }
    },
    {
      "token": "度胸",
      "isbns": {
        "9784569764085": 1
      }
    },
    {
      "token": "座る",
      "isbns": {
        "9784041041413": 1
      }
    },
    {
      "token": "座標",
      "isbns": {
        "9784339023992": 8,
        "9784785310936": 1
      }
    },
    {
      "token": "座標軸",
      "isbns": {
        "9784569845999": 1
      }
    },
    {
      "token": "庶民",
      "isbns": {
        "9784569665511": 1
      }
    },
    {
      "token": "廃れる",
      "isbns": {
        "9784296109272": 1
      }
    },
    {
      "token": "延びる",
      "isbns": {
        "9784492533871": 2
      }
    },
    {
      "token": "建て",
      "isbns": {
        "9784569845999": 1
      }
    },
    {
      "token": "建ぺい率",
      "isbns": {
        "9784322130560": 1
      }
    },
    {
      "token": "建国",
      "isbns": {
        "9784047033757": 1,
        "9784562032495": 1,
        "9784806124948": 1
      }
    },
    {
      "token": "建材",
      "isbns": {
        "9784408421049": 1
      }
    },
    {
      "token": "建武",
      "isbns": {
        "9784866221090": 1
      }
    },
    {
      "token": "建物",
      "isbns": {
        "9784322130560": 2
      }
    },
    {
      "token": "建築",
      "isbns": {
        "9784322130560": 4
      }
    },
    {
      "token": "弁慶",
      "isbns": {
        "9784047033757": 1
      }
    },
    {
      "token": "弁証法",
      "isbns": {
        "9784768459416": 1
      }
    },
    {
      "token": "弊害",
      "isbns": {
        "9784044004347": 2
      }
    },
    {
      "token": "式量",
      "isbns": {
        "9784534047816": 2
      }
    },
    {
      "token": "引き上げる",
      "isbns": {
        "9784569845999": 1
      }
    },
    {
      "token": "引き寄せる",
      "isbns": {
        "9784041041413": 5,
        "9784894518049": 1
      }
    },
    {
      "token": "引き継ぐ",
      "isbns": {
        "9784166605248": 1
      }
    },
    {
      "token": "引く",
      "isbns": {
        "9784569845999": 1
      }
    },
    {
      "token": "引用",
      "isbns": {
        "9784254102772": 1,
        "9784339023992": 1
      }
    },
    {
      "token": "引退",
      "isbns": {
        "9784492533871": 1
      }
    },
    {
      "token": "引退後",
      "isbns": {
        "9784777830398": 1
      }
    },
    {
      "token": "弘法",
      "isbns": {
        "9784047033757": 1
      }
    },
    {
      "token": "弱い",
      "isbns": {
        "9784777830398": 1
      }
    },
    {
      "token": "弱み",
      "isbns": {
        "9784806135494": 1
      }
    },
    {
      "token": "弱点",
      "isbns": {
        "9784809031892": 1
      }
    },
    {
      "token": "弱者",
      "isbns": {
        "9784806140078": 3,
        "9784894518049": 1
      }
    },
    {
      "token": "強い",
      "isbns": {
        "4804750215": 1,
        "9784344032910": 1,
        "9784569764085": 1,
        "9784627847125": 1,
        "9784777830398": 2,
        "9784809031892": 1,
        "9784833425650": 2
      }
    },
    {
      "token": "強さ",
      "isbns": {
        "9784062923910": 1,
        "9784405105201": 3,
        "9784405108059": 1,
        "9784534047816": 1,
        "9784569764085": 2,
        "9784806135494": 1
      }
    },
    {
      "token": "強み",
      "isbns": {
        "9784041041413": 3,
        "9784806135494": 1,
        "9784809031892": 2
      }
    },
    {
      "token": "強制力",
      "isbns": {
        "9784833425650": 1
      }
    },
    {
      "token": "強敵",
      "isbns": {
        "9784569665511": 1
      }
    },
    {
      "token": "強毒",
      "isbns": {
        "9784883927616": 1
      }
    },
    {
      "token": "強硬",
      "isbns": {
        "9784569764085": 3
      }
    },
    {
      "token": "強者",
      "isbns": {
        "9784806140078": 2
      }
    },
    {
      "token": "強調",
      "isbns": {
        "9784047033757": 1
      }
    },
    {
      "token": "当たり",
      "isbns": {
        "9784569845999": 1
      }
    },
    {
      "token": "当たり前",
      "isbns": {
        "9784344032910": 1
      }
    },
    {
      "token": "当たる",
      "isbns": {
        "9784894512443": 1
      }
    },
    {
      "token": "当てはまる",
      "isbns": {
        "9784894518049": 1
      }
    },
    {
      "token": "当てる",
      "isbns": {
        "9784339023992": 1
      }
    },
    {
      "token": "当然",
      "isbns": {
        "9784777830398": 1
      }
    },
    {
      "token": "彝族",
      "isbns": {
        "9784047033757": 1
      }
    },
    {
      "token": "形作る",
      "isbns": {
        "9784120043079": 1,
        "9784344032910": 1
      }
    },
    {
      "token": "形式",
      "isbns": {
        "9784806124948": 1
      }
    },
    {
      "token": "形態",
      "isbns": {
        "9784254102772": 1
      }
    },
    {
      "token": "形成",
      "isbns": {
        "9784339023992": 1,
        "9784768459416": 1
      }
    },
    {
      "token": "形状",
      "isbns": {
        "9784339023992": 2
      }
    },
    {
      "token": "形而上学",
      "isbns": {
        "9784309464084": 1,
        "9784768459416": 1
      }
    },
    {
      "token": "形質",
      "isbns": {
        "9784873118338": 1
      }
    },
    {
      "token": "彩る",
      "isbns": {
        "9784569665511": 1
      }
    },
    {
      "token": "彩飾",
      "isbns": {
        "9784562030989": 1
      }
    },
    {
      "token": "影響",
      "isbns": {
        "9784047033757": 2,
        "9784309254548": 2,
        "9784339023992": 1,
        "9784489020001": 1,
        "9784569645742": 1,
        "9784777830398": 1,
        "9784798100234": 3,
        "9784816354090": 2
      }
    },
    {
      "token": "影響力",
      "isbns": {
        "9784777830398": 1
      }
    },
    {
      "token": "役割",
      "isbns": {
        "9784041041413": 1,
        "9784166605248": 1,
        "9784344032910": 1,
        "9784569845999": 1,
        "9784867931042": 1
      }
    },
    {
      "token": "役割分担",
      "isbns": {
        "9784809031892": 1
      }
    },
    {
      "token": "役目",
      "isbns": {
        "9784480064707": 1
      }
    },
    {
      "token": "役立つ",
      "isbns": {
        "9784331006054": 1,
        "9784489020001": 2,
        "9784894512443": 1
      }
    },
    {
      "token": "役者",
      "isbns": {
        "9784867931042": 1
      }
    },
    {
      "token": "彼女",
      "isbns": {
        "9784569665511": 1
      }
    },
    {
      "token": "征服",
      "isbns": {
        "4804750215": 1
      }
    },
    {
      "token": "待つ",
      "isbns": {
        "4804750215": 2,
        "9784798100234": 1,
        "9784799111406": 1,
        "9784909044662": 1
      }
    },
    {
      "token": "後奈良",
      "isbns": {
        "9784866221090": 1
      }
    },
    {
      "token": "後押し",
      "isbns": {
        "9784120043079": 1
      }
    }
  ]
}