{
  "page_num": 26,
  "isbns": [
    {
      "token": "いつ",
      "isbns": {
        "9784166605248": 1,
        "9784809031892": 1,
        "9784833425650": 1,
        "9784894518049": 1,
        "9784909044662": 1
      }
    },
    {
      "token": "いー",
      "isbns": {
        "9784594073879": 1,
        "9784809031892": 1
      }
    },
    {
      "token": "うけ",
      "isbns": {
        "9784331006054": 1
      }
    },
    {
      "token": "うさん",
      "isbns": {
        "9784166605248": 1
      }
    },
    {
      "token": "うち",
      "isbns": {
        "9784894518049": 2
      }
    },
    {
      "token": "うば",
      "isbns": {
        "9784047033757": 1
      }
    },
    {
      "token": "うまい",
      "isbns": {
        "9784569845999": 1,
        "9784828427669": 1,
        "9784894512443": 1,
        "9784909044662": 2
      }
    },
    {
      "token": "うる",
      "isbns": {
        "9784044004347": 1
      }
    },
    {
      "token": "うれしい",
      "isbns": {
        "9784833425650": 1
      }
    },
    {
      "token": "おう",
      "isbns": {
        "9784047033757": 1
      }
    },
    {
      "token": "おかしな",
      "isbns": {
        "9784909044662": 1
      }
    },
    {
      "token": "おじ",
      "isbns": {
        "9784909044662": 1
      }
    },
    {
      "token": "おちる",
      "isbns": {
        "9784166605248": 1
      }
    },
    {
      "token": "おもしろい",
      "isbns": {
        "9784909044662": 1
      }
    },
    {
      "token": "おもな",
      "isbns": {
        "9784044004347": 1
      }
    },
    {
      "token": "お客",
      "isbns": {
        "9784894518049": 8
      }
    },
    {
      "token": "お客さん",
      "isbns": {
        "9784894518049": 1
      }
    },
    {
      "token": "お店",
      "isbns": {
        "9784833425650": 1
      }
    },
    {
      "token": "お祭り",
      "isbns": {
        "9784909044662": 1
      }
    },
    {
      "token": "お粗末",
      "isbns": {
        "9784894518049": 1
      }
    }
  ]
}