{
  "page_num": 17,
  "isbns": [
    {
      "token": "412",
      "isbns": {
        "9784047033757": 1
      }
    },
    {
      "token": "414",
      "isbns": {
        "9784044004347": 1,
        "9784047033757": 1
      }
    },
    {
      "token": "415",
      "isbns": {
        "9784047033757": 1
      }
    },
    {
      "token": "416",
      "isbns": {
        "9784047033757": 3
      }
    },
    {
      "token": "417",
      "isbns": {
        "9784047033757": 1
      }
    },
    {
      "token": "418",
      "isbns": {
        "9784044004347": 1,
        "9784047033757": 1
      }
    },
    {
      "token": "419",
      "isbns": {
        "9784047033757": 3
      }
    },
    {
      "token": "420",
      "isbns": {
        "9784044004347": 1,
        "9784047033757": 1
      }
    },
    {
      "token": "423",
      "isbns": {
        "9784047033757": 1
      }
    },
    {
      "token": "424",
      "isbns": {
        "9784047033757": 1
      }
    },
    {
      "token": "425",
      "isbns": {
        "9784047033757": 1
      }
    },
    {
      "token": "426",
      "isbns": {
        "9784044004347": 1,
        "9784047033757": 2
      }
    },
    {
      "token": "427",
      "isbns": {
        "9784047033757": 1
      }
    },
    {
      "token": "428",
      "isbns": {
        "9784047033757": 3
      }
    },
    {
      "token": "429",
      "isbns": {
        "9784047033757": 1
      }
    },
    {
      "token": "43",
      "isbns": {
        "9784047033757": 5,
        "9784763195098": 1,
        "9784777830398": 1,
        "9784862760401": 1,
        "9784894512443": 1,
        "9784909044662": 1
      }
    },
    {
      "token": "430",
      "isbns": {
        "9784047033757": 2
      }
    },
    {
      "token": "431",
      "isbns": {
        "9784044004347": 1
      }
    },
    {
      "token": "432",
      "isbns": {
        "9784047033757": 3
      }
    },
    {
      "token": "433",
      "isbns": {
        "9784047033757": 2
      }
    }
  ]
}