{
  "page_num": 168,
  "isbns": [
    {
      "token": "許す",
      "isbns": {
        "9784833425650": 1,
        "9784894518049": 1
      }
    },
    {
      "token": "訳者",
      "isbns": {
        "9784763195098": 1
      }
    },
    {
      "token": "訴える",
      "isbns": {
        "9784166605248": 1
      }
    },
    {
      "token": "評価",
      "isbns": {
        "9784062815215": 1
      }
    },
    {
      "token": "評判",
      "isbns": {
        "9784492533871": 1
      }
    },
    {
      "token": "詠唱",
      "isbns": {
        "9784867931042": 1
      }
    },
    {
      "token": "試す",
      "isbns": {
        "9784828427669": 1
      }
    },
    {
      "token": "試練",
      "isbns": {
        "9784777830398": 2
      }
    },
    {
      "token": "試金石",
      "isbns": {
        "4-8047-5021-5": 1
      }
    },
    {
      "token": "試験",
      "isbns": {
        "9784569845999": 1
      }
    },
    {
      "token": "話し方",
      "isbns": {
        "9784909044662": 1
      }
    },
    {
      "token": "詳細化",
      "isbns": {
        "9784569845999": 1
      }
    },
    {
      "token": "誇り",
      "isbns": {
        "9784166605248": 2,
        "9784594073879": 1
      }
    },
    {
      "token": "誕生",
      "isbns": {
        "9784047033757": 4,
        "9784331006054": 2
      }
    },
    {
      "token": "誘う",
      "isbns": {
        "9784062815215": 1,
        "9784833425650": 1
      }
    },
    {
      "token": "語る",
      "isbns": {
        "9784569665511": 1,
        "9784777830398": 2
      }
    },
    {
      "token": "語れる",
      "isbns": {
        "9784344032910": 1
      }
    },
    {
      "token": "語感",
      "isbns": {
        "9784166605248": 1
      }
    },
    {
      "token": "誠実",
      "isbns": {
        "9784833425650": 1
      }
    },
    {
      "token": "誤解",
      "isbns": {
        "4-8047-5021-5": 3,
        "9784166605248": 1,
        "9784894518049": 1
      }
    }
  ]
}